candig_rnaget/__init__.py
candig_rnaget/app.py
candig_rnaget/api/__init__.py
candig_rnaget/api/exceptions.py
candig_rnaget/api/logging.py
candig_rnaget/api/models.py
candig_rnaget/api/operations.py
candig_rnaget/api/rnaget.yaml
candig_rnaget/auth/__init__.py
candig_rnaget/expression/__init__.py
candig_rnaget/expression/download.py
candig_rnaget/expression/feature_mapping_HGNC.tsv
candig_rnaget/expression/rnaget_query.py
candig_rnaget/orm/__init__.py
candig_rnaget/orm/filters_expression.json
candig_rnaget/orm/filters_search.json
candig_rnaget/orm/guid.py
candig_rnaget/orm/models.py
candig_rnaget/orm/tests.py
candig_rnaget/scripts/__init__.py
candig_rnaget/scripts/post_data.py
candig_rnaget/scripts/post_project.py
candig_rnaget/scripts/post_study.py
candig_rnaget/scripts/quants2hdf.py
candig_rnaget-0.9.3.data/data/api/rnaget.yaml
candig_rnaget-0.9.3.data/data/data/feature_mapping_HGNC.tsv
candig_rnaget-0.9.3.data/data/data/filters_expression.json
candig_rnaget-0.9.3.data/data/data/filters_search.json
candig_rnaget-0.9.3.dist-info/LICENSE
candig_rnaget-0.9.3.dist-info/METADATA
candig_rnaget-0.9.3.dist-info/WHEEL
candig_rnaget-0.9.3.dist-info/entry_points.txt
candig_rnaget-0.9.3.dist-info/top_level.txt
candig_rnaget-0.9.3.dist-info/RECORD
