Metadata-Version: 2.1
Name: candig-rnaget
Version: 0.9.3
Summary: A POC implementation of GA4GH RNAGET API
Home-page: https://github.com/CanDIG/rnaget_service
Author: BCGSC
Author-email: alipski@bcgsc.ca
License: GNU General Public License v3
Download-URL: https://github.com/CanDIG/rnaget_service/archive/v0.9.3.tar.gz
Keywords: candig_rnaget
Platform: UNKNOWN
Classifier: Development Status :: 2 - Pre-Alpha
Classifier: Intended Audience :: Developers
Classifier: License :: OSI Approved :: GNU General Public License v3 (GPLv3)
Classifier: Natural Language :: English
Classifier: Programming Language :: Python :: 3
Classifier: Programming Language :: Python :: 3.4
Classifier: Programming Language :: Python :: 3.5
Classifier: Programming Language :: Python :: 3.6
Classifier: Programming Language :: Python :: 3.7
Requires-Dist: jsonschema (==2.6.0)
Requires-Dist: connexion (==2.2.0)
Requires-Dist: SQLAlchemy (==1.3.0)
Requires-Dist: tornado (==6.0.1)
Requires-Dist: decorator (==4.3.2)
Requires-Dist: bravado-core (==5.10.2)
Requires-Dist: pyyaml (>=4.2b1)
Requires-Dist: h5py (==2.9.0)
Requires-Dist: swagger-ui-bundle (==0.0.3)
Requires-Dist: pandas (==0.24.2)
Requires-Dist: loompy (==2.0.17)
Requires-Dist: rfc3987 (==1.3.8)
Requires-Dist: strict-rfc3339 (==0.7)
Requires-Dist: webcolors (==1.8.1)
